{
  "_comment": "PLACEHOLDER VALUES - Replace with actual values from APK decompilation",
  "_status": "NEEDS_VERIFICATION",

  "board_size": 8,
  "batch_size": 3,

  "blocks": {
    "single": [[1]],

    "line_2h": [[1, 1]],
    "line_3h": [[1, 1, 1]],

    "line_2v": [[1], [1]],
    "line_3v": [[1], [1], [1]],

    "square_2x2": [[1, 1], [1, 1]],
    "square_3x3": [[1, 1, 1], [1, 1, 1], [1, 1, 1]],

    "L_2x2": [[1, 0], [1, 1]],
    "L_2x2_90": [[1, 1], [1, 0]],
    "L_2x2_180": [[1, 1], [0, 1]],
    "L_2x2_270": [[0, 1], [1, 1]],

    "L_3x2": [[1, 0], [1, 0], [1, 1]],
    "L_3x2_90": [[1, 1, 1], [1, 0, 0]],
    "L_3x2_180": [[1, 1], [0, 1], [0, 1]],
    "L_3x2_270": [[0, 0, 1], [1, 1, 1]],

    "L_2x3": [[1, 0, 0], [1, 1, 1]],
    "L_2x3_90": [[1, 1], [1, 0], [1, 0]],
    "L_2x3_180": [[1, 1, 1], [0, 0, 1]],
    "L_2x3_270": [[0, 1], [0, 1], [1, 1]],

    "T_2x3": [[1, 1, 1], [0, 1, 0]],
    "T_2x3_90": [[0, 1], [1, 1], [0, 1]],
    "T_2x3_180": [[0, 1, 0], [1, 1, 1]],
    "T_2x3_270": [[1, 0], [1, 1], [1, 0]],

    "Z_2x3": [[1, 1, 0], [0, 1, 1]],
    "Z_2x3_90": [[0, 1], [1, 1], [1, 0]],
    "S_2x3": [[0, 1, 1], [1, 1, 0]],
    "S_2x3_90": [[1, 0], [1, 1], [0, 1]]
  },

  "spawn_weights": {
    "_comment": "Weights determine how likely each block is to spawn. Higher = more common.",
    "single": 1.0,
    "line_2h": 1.0,
    "line_3h": 1.0,
    "line_2v": 1.0,
    "line_3v": 1.0,
    "square_2x2": 1.0,
    "square_3x3": 0.5,
    "L_2x2": 1.0,
    "L_2x2_90": 1.0,
    "L_2x2_180": 1.0,
    "L_2x2_270": 1.0,
    "L_3x2": 0.8,
    "L_3x2_90": 0.8,
    "L_3x2_180": 0.8,
    "L_3x2_270": 0.8,
    "L_2x3": 0.8,
    "L_2x3_90": 0.8,
    "L_2x3_180": 0.8,
    "L_2x3_270": 0.8,
    "T_2x3": 0.8,
    "T_2x3_90": 0.8,
    "T_2x3_180": 0.8,
    "T_2x3_270": 0.8,
    "Z_2x3": 0.7,
    "Z_2x3_90": 0.7,
    "S_2x3": 0.7,
    "S_2x3_90": 0.7
  },

  "scoring": {
    "_comment": "PLACEHOLDER - Extract actual values from APK",
    "points_per_cell": 1,
    "line_clear_base": 10,
    "simultaneous_multiplier": 1.5,
    "combo_base_bonus": 5,
    "combo_multiplier": 1.0,
    "perfect_clear_bonus": 100
  }
}
